flashrl/__init__.py
flashrl/main.py
flashrl/models.py
flashrl/utils.py
flashrl/envs/__init__.py
flashrl/envs/grid.c
flashrl/envs/grid.cpython-311-x86_64-linux-gnu.so
flashrl/envs/grid.pyx
flashrl/envs/multigrid.c
flashrl/envs/multigrid.cpython-311-x86_64-linux-gnu.so
flashrl/envs/multigrid.pyx
flashrl/envs/pong.c
flashrl/envs/pong.cpython-311-x86_64-linux-gnu.so
flashrl/envs/pong.pyx
flashrl-0.2.1.dist-info/METADATA
flashrl-0.2.1.dist-info/WHEEL
flashrl-0.2.1.dist-info/top_level.txt
flashrl-0.2.1.dist-info/RECORD
