Metadata-Version: 2.2
Name: flashrl
Version: 0.2.1
Summary: Fast reinforcement learning 💨
Author-email: codingfisch <l_fisc17@wwu.de>
Requires-Dist: torch
Requires-Dist: Cython
Requires-Dist: tqdm
Requires-Dist: plotille
Requires-Dist: tensorboard
